tkwebview2/__init__.py
tkwebview2/bind.py
tkwebview2/tkwebview2.py
tkwebview2-3.4.0.dist-info/LICENSE.txt
tkwebview2-3.4.0.dist-info/METADATA
tkwebview2-3.4.0.dist-info/WHEEL
tkwebview2-3.4.0.dist-info/top_level.txt
tkwebview2-3.4.0.dist-info/RECORD
