Metadata-Version: 2.1
Name: tkwebview2
Version: 3.4.0
Summary: tkinter-WebView2 widget, based on WebView2.Core
Home-page: https://github.com/Smart-Space/tkwebview2
Author: Smart-Space
Author-email: smart-space@qq.com
License: MIT License
Classifier: Intended Audience :: Developers
Classifier: Operating System :: Microsoft :: Windows
Classifier: Natural Language :: Chinese (Simplified)
Classifier: Programming Language :: Python
Classifier: Programming Language :: Python :: 3
Classifier: License :: OSI Approved :: MIT License
Classifier: Topic :: Software Development :: Libraries
Requires-Python: >=3.6
License-File: LICENSE.txt
Requires-Dist: pythonnet
Requires-Dist: pywebview
